setup.py
xmgrace_parser.py
xmgrace_parser.egg-info/PKG-INFO
xmgrace_parser.egg-info/SOURCES.txt
xmgrace_parser.egg-info/dependency_links.txt
xmgrace_parser.egg-info/entry_points.txt
xmgrace_parser.egg-info/top_level.txt