Metadata-Version: 1.0
Name: xmgrace-parser
Version: 1.0.1
Summary: Modifying xmgrace agr files interactively in ipython
Home-page: https://github.com/goerz/xmgrace_parser
Author: Michael Goerz
Author-email: mail@michaelgoerz.net
License: GPL
Platform: UNKNOWN
